latex_generator_neimess_itmo/__init__.py
latex_generator_neimess_itmo/latex_utils.py
latex_generator_neimess_itmo-0.1.2.dist-info/LICENSE
latex_generator_neimess_itmo-0.1.2.dist-info/METADATA
latex_generator_neimess_itmo-0.1.2.dist-info/WHEEL
latex_generator_neimess_itmo-0.1.2.dist-info/top_level.txt
latex_generator_neimess_itmo-0.1.2.dist-info/RECORD
