Metadata-Version: 2.2
Name: latex_generator_neimess_itmo
Version: 0.1.2
Summary: ITMO-lab-2-project
Author: Maxim Gavrilenko
Author-email: sh0ckerZ7714@gmail.com
Requires-Python: >=3.10
License-File: LICENSE
Dynamic: author
Dynamic: author-email
Dynamic: requires-python
